Metadata-Version: 2.1
Name: wsdk
Version: 0.1
Summary: Weather SDK for accessing a weather API
Author: Dmitrii Liuzin
